.dada-version
MANIFEST.in
README.md
requirements.txt
setup.cfg
setup.py
dada_utils/__init__.py
dada_utils/dates.py
dada_utils/etc.py
dada_utils/path.py
dada_utils.egg-info/PKG-INFO
dada_utils.egg-info/SOURCES.txt
dada_utils.egg-info/dependency_links.txt
dada_utils.egg-info/requires.txt
dada_utils.egg-info/top_level.txt
dada_utils/tests/__init__.py
dada_utils/tests/test_utils.py