Metadata-Version: 1.0
Name: dada-utils
Version: 0.0.9
Summary: Python utilities used throughout dada-lake
Home-page: http://globally.ltd
Author: gltd
Author-email: hey@gltd.email
License: UNKNOWN
Platform: UNKNOWN
